<?xml version="1.0" encoding="UTF-8" ?>
<!DOCTYPE mapper PUBLIC "-//mybatis.org//DTD Mapper 3.0//EN" "http://mybatis.org/dtd/mybatis-3-mapper.dtd" >
<mapper namespace="com.project.dao.QuestionDataMapper" >
  <resultMap id="BaseResultMap" type="com.project.model.QuestionData" >
    <!--
      WARNING - @mbggenerated
      This element is automatically generated by MyBatis Generator, do not modify.
      This element was generated on Fri Sep 08 10:01:11 CST 2017.
    -->
    <id column="questionID" property="questionid" jdbcType="BIGINT" />
    <result column="askID" property="askid" jdbcType="BIGINT" />
    <result column="questionTitle" property="questiontitle" jdbcType="VARCHAR" />
    <result column="questionTagID" property="questiontagid" jdbcType="BIGINT" />
    <result column="questionDiscription" property="questiondiscription" jdbcType="VARCHAR" />
    <result column="questionDate" property="questiondate" jdbcType="TIMESTAMP" />
    <result column="questionPV" property="questionpv" jdbcType="INTEGER" />
    <result column="questionUrl" property="questionurl" jdbcType="VARCHAR" />
    <result column="questionValidPV" property="questionvalidpv" jdbcType="INTEGER" />
  </resultMap>
  <sql id="Example_Where_Clause" >
    <!--
      WARNING - @mbggenerated
      This element is automatically generated by MyBatis Generator, do not modify.
      This element was generated on Fri Sep 08 10:01:11 CST 2017.
    -->
    <where >
      <foreach collection="oredCriteria" item="criteria" separator="or" >
        <if test="criteria.valid" >
          <trim prefix="(" suffix=")" prefixOverrides="and" >
            <foreach collection="criteria.criteria" item="criterion" >
              <choose >
                <when test="criterion.noValue" >
                  and ${criterion.condition}
                </when>
                <when test="criterion.singleValue" >
                  and ${criterion.condition} #{criterion.value}
                </when>
                <when test="criterion.betweenValue" >
                  and ${criterion.condition} #{criterion.value} and #{criterion.secondValue}
                </when>
                <when test="criterion.listValue" >
                  and ${criterion.condition}
                  <foreach collection="criterion.value" item="listItem" open="(" close=")" separator="," >
                    #{listItem}
                  </foreach>
                </when>
              </choose>
            </foreach>
          </trim>
        </if>
      </foreach>
    </where>
  </sql>
  <sql id="Update_By_Example_Where_Clause" >
    <!--
      WARNING - @mbggenerated
      This element is automatically generated by MyBatis Generator, do not modify.
      This element was generated on Fri Sep 08 10:01:11 CST 2017.
    -->
    <where >
      <foreach collection="example.oredCriteria" item="criteria" separator="or" >
        <if test="criteria.valid" >
          <trim prefix="(" suffix=")" prefixOverrides="and" >
            <foreach collection="criteria.criteria" item="criterion" >
              <choose >
                <when test="criterion.noValue" >
                  and ${criterion.condition}
                </when>
                <when test="criterion.singleValue" >
                  and ${criterion.condition} #{criterion.value}
                </when>
                <when test="criterion.betweenValue" >
                  and ${criterion.condition} #{criterion.value} and #{criterion.secondValue}
                </when>
                <when test="criterion.listValue" >
                  and ${criterion.condition}
                  <foreach collection="criterion.value" item="listItem" open="(" close=")" separator="," >
                    #{listItem}
                  </foreach>
                </when>
              </choose>
            </foreach>
          </trim>
        </if>
      </foreach>
    </where>
  </sql>
  <sql id="Base_Column_List" >
    <!--
      WARNING - @mbggenerated
      This element is automatically generated by MyBatis Generator, do not modify.
      This element was generated on Fri Sep 08 10:01:11 CST 2017.
    -->
    questionID, askID, questionTitle, questionTagID, questionDiscription, questionDate, 
    questionPV, questionUrl, questionValidPV
  </sql>
  <select id="selectByExample" resultMap="BaseResultMap" parameterType="com.project.model.QuestionDataExample" >
    <!--
      WARNING - @mbggenerated
      This element is automatically generated by MyBatis Generator, do not modify.
      This element was generated on Fri Sep 08 10:01:11 CST 2017.
    -->
    select
    <if test="distinct" >
      distinct
    </if>
    <include refid="Base_Column_List" />
    from questioninfo_
    <if test="_parameter != null" >
      <include refid="Example_Where_Clause" />
    </if>
    <if test="orderByClause != null" >
      order by ${orderByClause}
    </if>
  </select>
  <select id="selectByPrimaryKey" resultMap="BaseResultMap" parameterType="java.lang.Long" >
    <!--
      WARNING - @mbggenerated
      This element is automatically generated by MyBatis Generator, do not modify.
      This element was generated on Fri Sep 08 10:01:11 CST 2017.
    -->
    select 
    <include refid="Base_Column_List" />
    from questioninfo_
    where questionID = #{questionid,jdbcType=BIGINT}
  </select>
  <delete id="deleteByPrimaryKey" parameterType="java.lang.Long" >
    <!--
      WARNING - @mbggenerated
      This element is automatically generated by MyBatis Generator, do not modify.
      This element was generated on Fri Sep 08 10:01:11 CST 2017.
    -->
    delete from questioninfo_
    where questionID = #{questionid,jdbcType=BIGINT}
  </delete>
  <delete id="deleteByExample" parameterType="com.project.model.QuestionDataExample" >
    <!--
      WARNING - @mbggenerated
      This element is automatically generated by MyBatis Generator, do not modify.
      This element was generated on Fri Sep 08 10:01:11 CST 2017.
    -->
    delete from questioninfo_
    <if test="_parameter != null" >
      <include refid="Example_Where_Clause" />
    </if>
  </delete>
  <insert id="insert" parameterType="com.project.model.QuestionData" >
    <!--
      WARNING - @mbggenerated
      This element is automatically generated by MyBatis Generator, do not modify.
      This element was generated on Fri Sep 08 10:01:11 CST 2017.
    -->
    insert into questioninfo_ (questionID, askID, questionTitle, 
      questionTagID, questionDiscription, questionDate, 
      questionPV, questionUrl, questionValidPV
      )
    values (#{questionid,jdbcType=BIGINT}, #{askid,jdbcType=BIGINT}, #{questiontitle,jdbcType=VARCHAR}, 
      #{questiontagid,jdbcType=BIGINT}, #{questiondiscription,jdbcType=VARCHAR}, #{questiondate,jdbcType=TIMESTAMP}, 
      #{questionpv,jdbcType=INTEGER}, #{questionurl,jdbcType=VARCHAR}, #{questionvalidpv,jdbcType=INTEGER}
      )
  </insert>
  <insert id="insertSelective" parameterType="com.project.model.QuestionData" >
    <!--
      WARNING - @mbggenerated
      This element is automatically generated by MyBatis Generator, do not modify.
      This element was generated on Fri Sep 08 10:01:11 CST 2017.
    -->
    insert into questioninfo_
    <trim prefix="(" suffix=")" suffixOverrides="," >
      <if test="questionid != null" >
        questionID,
      </if>
      <if test="askid != null" >
        askID,
      </if>
      <if test="questiontitle != null" >
        questionTitle,
      </if>
      <if test="questiontagid != null" >
        questionTagID,
      </if>
      <if test="questiondiscription != null" >
        questionDiscription,
      </if>
      <if test="questiondate != null" >
        questionDate,
      </if>
      <if test="questionpv != null" >
        questionPV,
      </if>
      <if test="questionurl != null" >
        questionUrl,
      </if>
      <if test="questionvalidpv != null" >
        questionValidPV,
      </if>
    </trim>
    <trim prefix="values (" suffix=")" suffixOverrides="," >
      <if test="questionid != null" >
        #{questionid,jdbcType=BIGINT},
      </if>
      <if test="askid != null" >
        #{askid,jdbcType=BIGINT},
      </if>
      <if test="questiontitle != null" >
        #{questiontitle,jdbcType=VARCHAR},
      </if>
      <if test="questiontagid != null" >
        #{questiontagid,jdbcType=BIGINT},
      </if>
      <if test="questiondiscription != null" >
        #{questiondiscription,jdbcType=VARCHAR},
      </if>
      <if test="questiondate != null" >
        #{questiondate,jdbcType=TIMESTAMP},
      </if>
      <if test="questionpv != null" >
        #{questionpv,jdbcType=INTEGER},
      </if>
      <if test="questionurl != null" >
        #{questionurl,jdbcType=VARCHAR},
      </if>
      <if test="questionvalidpv != null" >
        #{questionvalidpv,jdbcType=INTEGER},
      </if>
    </trim>
  </insert>
  <select id="countByExample" parameterType="com.project.model.QuestionDataExample" resultType="java.lang.Integer" >
    <!--
      WARNING - @mbggenerated
      This element is automatically generated by MyBatis Generator, do not modify.
      This element was generated on Fri Sep 08 10:01:11 CST 2017.
    -->
    select count(*) from questioninfo_
    <if test="_parameter != null" >
      <include refid="Example_Where_Clause" />
    </if>
  </select>
  <update id="updateByExampleSelective" parameterType="map" >
    <!--
      WARNING - @mbggenerated
      This element is automatically generated by MyBatis Generator, do not modify.
      This element was generated on Fri Sep 08 10:01:11 CST 2017.
    -->
    update questioninfo_
    <set >
      <if test="record.questionid != null" >
        questionID = #{record.questionid,jdbcType=BIGINT},
      </if>
      <if test="record.askid != null" >
        askID = #{record.askid,jdbcType=BIGINT},
      </if>
      <if test="record.questiontitle != null" >
        questionTitle = #{record.questiontitle,jdbcType=VARCHAR},
      </if>
      <if test="record.questiontagid != null" >
        questionTagID = #{record.questiontagid,jdbcType=BIGINT},
      </if>
      <if test="record.questiondiscription != null" >
        questionDiscription = #{record.questiondiscription,jdbcType=VARCHAR},
      </if>
      <if test="record.questiondate != null" >
        questionDate = #{record.questiondate,jdbcType=TIMESTAMP},
      </if>
      <if test="record.questionpv != null" >
        questionPV = #{record.questionpv,jdbcType=INTEGER},
      </if>
      <if test="record.questionurl != null" >
        questionUrl = #{record.questionurl,jdbcType=VARCHAR},
      </if>
      <if test="record.questionvalidpv != null" >
        questionValidPV = #{record.questionvalidpv,jdbcType=INTEGER},
      </if>
    </set>
    <if test="_parameter != null" >
      <include refid="Update_By_Example_Where_Clause" />
    </if>
  </update>
  <update id="updateByExample" parameterType="map" >
    <!--
      WARNING - @mbggenerated
      This element is automatically generated by MyBatis Generator, do not modify.
      This element was generated on Fri Sep 08 10:01:11 CST 2017.
    -->
    update questioninfo_
    set questionID = #{record.questionid,jdbcType=BIGINT},
      askID = #{record.askid,jdbcType=BIGINT},
      questionTitle = #{record.questiontitle,jdbcType=VARCHAR},
      questionTagID = #{record.questiontagid,jdbcType=BIGINT},
      questionDiscription = #{record.questiondiscription,jdbcType=VARCHAR},
      questionDate = #{record.questiondate,jdbcType=TIMESTAMP},
      questionPV = #{record.questionpv,jdbcType=INTEGER},
      questionUrl = #{record.questionurl,jdbcType=VARCHAR},
      questionValidPV = #{record.questionvalidpv,jdbcType=INTEGER}
    <if test="_parameter != null" >
      <include refid="Update_By_Example_Where_Clause" />
    </if>
  </update>
  <update id="updateByPrimaryKeySelective" parameterType="com.project.model.QuestionData" >
    <!--
      WARNING - @mbggenerated
      This element is automatically generated by MyBatis Generator, do not modify.
      This element was generated on Fri Sep 08 10:01:11 CST 2017.
    -->
    update questioninfo_
    <set >
      <if test="askid != null" >
        askID = #{askid,jdbcType=BIGINT},
      </if>
      <if test="questiontitle != null" >
        questionTitle = #{questiontitle,jdbcType=VARCHAR},
      </if>
      <if test="questiontagid != null" >
        questionTagID = #{questiontagid,jdbcType=BIGINT},
      </if>
      <if test="questiondiscription != null" >
        questionDiscription = #{questiondiscription,jdbcType=VARCHAR},
      </if>
      <if test="questiondate != null" >
        questionDate = #{questiondate,jdbcType=TIMESTAMP},
      </if>
      <if test="questionpv != null" >
        questionPV = #{questionpv,jdbcType=INTEGER},
      </if>
      <if test="questionurl != null" >
        questionUrl = #{questionurl,jdbcType=VARCHAR},
      </if>
      <if test="questionvalidpv != null" >
        questionValidPV = #{questionvalidpv,jdbcType=INTEGER},
      </if>
    </set>
    where questionID = #{questionid,jdbcType=BIGINT}
  </update>
  <update id="updateByPrimaryKey" parameterType="com.project.model.QuestionData" >
    <!--
      WARNING - @mbggenerated
      This element is automatically generated by MyBatis Generator, do not modify.
      This element was generated on Fri Sep 08 10:01:11 CST 2017.
    -->
    update questioninfo_
    set askID = #{askid,jdbcType=BIGINT},
      questionTitle = #{questiontitle,jdbcType=VARCHAR},
      questionTagID = #{questiontagid,jdbcType=BIGINT},
      questionDiscription = #{questiondiscription,jdbcType=VARCHAR},
      questionDate = #{questiondate,jdbcType=TIMESTAMP},
      questionPV = #{questionpv,jdbcType=INTEGER},
      questionUrl = #{questionurl,jdbcType=VARCHAR},
      questionValidPV = #{questionvalidpv,jdbcType=INTEGER}
    where questionID = #{questionid,jdbcType=BIGINT}
  </update>
</mapper>